rl_toolkit/__init__.py
rl_toolkit/__main__.py
rl_toolkit/core/__init__.py
rl_toolkit/core/process.py
rl_toolkit/core/wrappers/__init__.py
rl_toolkit/core/wrappers/dm_control.py
rl_toolkit/core/wrappers/frame_stack.py
rl_toolkit/core/wrappers/humanoid.py
rl_toolkit/networks/__init__.py
rl_toolkit/networks/callbacks/__init__.py
rl_toolkit/networks/callbacks/dqn_agent.py
rl_toolkit/networks/callbacks/lr.py
rl_toolkit/networks/callbacks/sac_agent.py
rl_toolkit/networks/layers/__init__.py
rl_toolkit/networks/layers/noise.py
rl_toolkit/networks/models/__init__.py
rl_toolkit/networks/models/actor.py
rl_toolkit/networks/models/actor_critic.py
rl_toolkit/networks/models/critic.py
rl_toolkit/networks/models/dueling.py
rl_toolkit/utils/__init__.py
rl_toolkit/utils/replay_buffer.py
rl_toolkit/utils/variable_container.py
rl_toolkit-5.0.0.dist-info/LICENSE.txt
rl_toolkit-5.0.0.dist-info/METADATA
rl_toolkit-5.0.0.dist-info/WHEEL
rl_toolkit-5.0.0.dist-info/entry_points.txt
rl_toolkit-5.0.0.dist-info/top_level.txt
rl_toolkit-5.0.0.dist-info/RECORD
