Metadata-Version: 2.1
Name: rl-toolkit
Version: 5.0.0
Summary: RL-Toolkit: A Research Framework for Robotics
Home-page: https://github.com/markub3327/rl-toolkit
Download-URL: https://github.com/markub3327/rl-toolkit/releases
Author: Martin Kubovcik
Author-email: markub3327@gmail.com
License: MIT License
Project-URL: Bug Tracker, https://github.com/markub3327/rl-toolkit/issues
Keywords: reinforcement-learning,ml,gymnasium,reverb,docker,rl-agents,rl,sac,rl-algorithms,soft-actor-critic,gsde,rl-toolkit,games,tensorflow,wandb
Classifier: License :: OSI Approved :: MIT License
Classifier: Environment :: Console
Classifier: Environment :: GPU :: NVIDIA CUDA
Classifier: Intended Audience :: Science/Research
Classifier: Intended Audience :: Education
Classifier: Topic :: Scientific/Engineering :: Artificial Intelligence
Classifier: Programming Language :: Python :: 3.9
Classifier: Programming Language :: Python :: 3.10
Classifier: Programming Language :: Python :: 3.11
Requires-Python: >=3.9
License-File: LICENSE.txt
Requires-Dist: gymnasium
Requires-Dist: box2d-py
Requires-Dist: pygame
Requires-Dist: swig
Requires-Dist: dm-control
Requires-Dist: tensorflow-probability==0.22.1
Requires-Dist: wandb
Requires-Dist: pyyaml
Requires-Dist: lxml
Provides-Extra: all
Requires-Dist: dm-reverb; extra == "all"
Requires-Dist: flappy-bird-gymnasium; extra == "all"
Provides-Extra: reverb
Requires-Dist: dm-reverb; extra == "reverb"
Provides-Extra: tf
Requires-Dist: tensorflow==2.14.0; extra == "tf"
